Metadata-Version: 1.1
Name: plugnplay
Version: 0.5.4
Summary: A Generic plug-in system for python
Home-page: http://github.com/daltonmatos/plugnplay
Author: Dalton Barreto
Author-email: daltonmatos@gmail.com
License: GPLv2
Platform: UNKNOWN
Classifier: License :: OSI Approved :: GNU General Public License (GPL)
Classifier: Operating System :: OS Independent
Classifier: Programming Language :: Python
Classifier: Programming Language :: Python :: 3
Classifier: Topic :: Software Development :: Libraries :: Application Frameworks
